hdmi/__init__.py
hdmi/builders/__init__.py
hdmi/builders/default.py
hdmi/containers/__init__.py
hdmi/containers/default.py
hdmi/containers/scoped.py
hdmi/exceptions.py
hdmi/py.typed
hdmi/types/__init__.py
hdmi/types/containers.py
hdmi/types/definitions.py
hdmi/utils/__init__.py
hdmi/utils/typing.py
hdmi-0.1.0.dist-info/WHEEL
hdmi-0.1.0.dist-info/METADATA
hdmi-0.1.0.dist-info/RECORD
