Metadata-Version: 2.3
Name: hdmi
Version: 0.1.0
Summary: A dependency injection framework for Python with dynamic late-binding resolution
Author: Romain Dorgueil
Author-email: Romain Dorgueil <romain@makersquad.fr>
License: MIT License
Requires-Dist: anyio>=4.0.0
Requires-Dist: pytest>=8.0.0 ; extra == 'dev'
Requires-Dist: pytest-cov>=4.1.0 ; extra == 'dev'
Requires-Dist: ruff>=0.8.0 ; extra == 'dev'
Requires-Dist: basedpyright>=1.21.0 ; extra == 'dev'
Requires-Dist: sphinx>=8.0.0 ; extra == 'dev'
Requires-Dist: sphinx-autobuild>=2024.0.0 ; extra == 'dev'
Requires-Dist: furo>=2024.0.0 ; extra == 'dev'
Requires-Dist: sphinxcontrib-mermaid>=1.0.0 ; extra == 'dev'
Requires-Dist: twine>=6.0.0 ; extra == 'dev'
Requires-Python: >=3.13
Provides-Extra: dev
